Metadata-Version: 2.1
Name: PyFileCP
Version: 0.1
Summary: Python Package For Copying Files
Home-page: https://github.com/re-mc/PyFileCP/
Download-URL: https://github.com/re-mc/PyFileCP/archive/v0.1.tar.gz
Author: Wyatt DaviesWoods
Author-email: wynotswitch@gmail.com
License: MIT
Keywords: copy,file,simple
Platform: UNKNOWN
Classifier: Development Status :: 3 - Alpha
Classifier: Intended Audience :: Developers
Classifier: Topic :: Software Development :: Build Tools
Classifier: License :: OSI Approved :: MIT License
Classifier: Programming Language :: Python :: 3
Classifier: Programming Language :: Python :: 3.4
Classifier: Programming Language :: Python :: 3.5
Classifier: Programming Language :: Python :: 3.6
License-File: LICENCE.txt
